uwatermelon/__init__.py
uwatermelon/dialog.py
uwatermelon/main.py
uwatermelon/web.py
uwatermelon-0.1.5.dist-info/licenses/LICENSE
uwatermelon-0.1.5.dist-info/METADATA
uwatermelon-0.1.5.dist-info/WHEEL
uwatermelon-0.1.5.dist-info/top_level.txt
uwatermelon-0.1.5.dist-info/RECORD
