Metadata-Version: 2.4
Name: uwatermelon
Version: 0.1.5
Summary: 日本語で書ける謎の言語「うぉーたーめろん」
Author: Exe猫
Classifier: Programming Language :: Python :: 3
Classifier: Operating System :: OS Independent
Classifier: License :: OSI Approved :: MIT License
Classifier: Natural Language :: Japanese
Requires-Python: >=3.6
License-File: LICENSE
Dynamic: author
Dynamic: classifier
Dynamic: description
Dynamic: description-content-type
Dynamic: license-file
Dynamic: requires-python
Dynamic: summary
